scanf.py
scanf-1.5.2.dist-info/METADATA
scanf-1.5.2.dist-info/RECORD
scanf-1.5.2.dist-info/WHEEL
scanf-1.5.2.dist-info/top_level.txt
