Metadata-Version: 2.1
Name: scanf
Version: 1.5.2
Summary: A small scanf implementation
Home-page: https://github.com/joshburnett/scanf
Author: Josh Burnett
Author-email: scanf@burnettsonline.org
License: MIT
Keywords: scanf
Platform: UNKNOWN
Classifier: Development Status :: 5 - Production/Stable
Classifier: Intended Audience :: Developers
Classifier: License :: OSI Approved :: MIT License
Classifier: Programming Language :: Python
Classifier: Programming Language :: Python :: 2.7
Classifier: Programming Language :: Python :: 3
